njsparser/__init__.py
njsparser/api.py
njsparser/cli.py
njsparser/parser/__init__.py
njsparser/parser/flight_data.py
njsparser/parser/manifests.py
njsparser/parser/next_data.py
njsparser/parser/types.py
njsparser/parser/urls.py
njsparser/source.py
njsparser/tools.py
njsparser/utils.py
njsparser-2.14.dist-info/METADATA
njsparser-2.14.dist-info/WHEEL
njsparser-2.14.dist-info/entry_points.txt
njsparser-2.14.dist-info/licenses/LICENSE
njsparser-2.14.dist-info/RECORD
