Metadata-Version: 2.4
Name: njsparser
Version: 2.14
Summary: A Python NextJS data parser from HTML
License-File: LICENSE
Author: ae
Author-email: 85891169+novitae@users.noreply.github.com
Requires-Python: >=3.10
Classifier: Programming Language :: Python :: 3
Classifier: Programming Language :: Python :: 3.10
Classifier: Programming Language :: Python :: 3.11
Classifier: Programming Language :: Python :: 3.12
Classifier: Programming Language :: Python :: 3.13
Classifier: Programming Language :: Python :: 3.14
Requires-Dist: lxml (>=6.0.0,<7.0.0)
Requires-Dist: orjson (>=3.10.18,<4.0.0)
Requires-Dist: pydantic (>=2.10.0,<3.0.0)
Requires-Dist: pythonmonkey (>=1.1.1,<2.0.0) ; python_version < "4.0"
Requires-Dist: requests (>=2.32.4,<3.0.0)
Requires-Dist: rich (>=14.0.0,<15.0.0)
Requires-Dist: typer (>=0.16.0,<0.17.0)
